hf_xet/__init__.py
hf_xet/hf_xet.abi3.so
hf_xet-1.1.9.dist-info/licenses/LICENSE
hf_xet-1.1.9.dist-info/METADATA
hf_xet-1.1.9.dist-info/WHEEL
hf_xet-1.1.9.dist-info/RECORD
