Metadata-Version: 2.4
Name: hf-xet
Version: 1.1.9
Classifier: License :: OSI Approved :: Apache Software License
Classifier: Programming Language :: Rust
Classifier: Programming Language :: Python :: Implementation :: CPython
Classifier: Programming Language :: Python :: Implementation :: PyPy
Classifier: Programming Language :: Python :: 3
Classifier: Programming Language :: Python :: 3 :: Only
Classifier: Programming Language :: Python :: 3.8
Classifier: Programming Language :: Python :: 3.9
Classifier: Programming Language :: Python :: 3.10
Classifier: Programming Language :: Python :: 3.11
Classifier: Programming Language :: Python :: 3.12
Classifier: Programming Language :: Python :: 3.13
Classifier: Topic :: Scientific/Engineering :: Artificial Intelligence
Requires-Dist: pytest ; extra == 'tests'
Provides-Extra: tests
License-File: LICENSE
Summary: Fast transfer of large files with the Hugging Face Hub.
Maintainer-email: Rajat Arya <rajat@rajatarya.com>, Jared Sulzdorf <j.sulzdorf@gmail.com>, Di Xiao <di@huggingface.co>, Assaf Vayner <assaf@huggingface.co>, Hoyt Koepke <hoytak@gmail.com>
License-Expression: Apache-2.0
Requires-Python: >=3.8
Project-URL: Homepage, https://github.com/huggingface/xet-core
Project-URL: Documentation, https://huggingface.co/docs/hub/en/storage-backends#using-xet-storage
Project-URL: Issues, https://github.com/huggingface/xet-core/issues
Project-URL: Repository, https://github.com/huggingface/xet-core.git
